lru/__init__.py
lru/cache.py
lru/compat.py
lru/decorators.py
lru_expiring_cache-1.1.dist-info/DESCRIPTION.rst
lru_expiring_cache-1.1.dist-info/METADATA
lru_expiring_cache-1.1.dist-info/RECORD
lru_expiring_cache-1.1.dist-info/WHEEL
lru_expiring_cache-1.1.dist-info/metadata.json
lru_expiring_cache-1.1.dist-info/top_level.txt
