Metadata-Version: 2.0
Name: lru-expiring-cache
Version: 1.1
Summary: LRU cache with that supports data expiration
Home-page: https://github.com/vpaliy/lru-cache
Author: Vasyl Paliy
Author-email: vpaliy97@gmail.com
License: MIT
Platform: UNKNOWN
Classifier: Intended Audience :: Developers
Classifier: Operating System :: OS Independent
Classifier: Programming Language :: Python
Classifier: Programming Language :: Python :: 3
Classifier: Programming Language :: Python :: 3.4
Classifier: Programming Language :: Python :: 3.5
Classifier: Programming Language :: Python :: 3.6
Requires-Python: >=2.7
Requires-Dist: six
Requires-Dist: future-fstrings
Requires-Dist: monotonic
